[{"id":1,"carID":12,"severity":3,"date":"2020-06-03T00:00:00.000Z"},{"id":2,"carID":5,"severity":4,"date":"2020-06-11T00:00:00.000Z"},{"id":3,"carID":13,"severity":1,"date":"2020-06-04T00:00:00.000Z"},{"id":4,"carID":11,"severity":4,"date":"2020-06-09T00:00:00.000Z"},{"id":5,"carID":8,"severity":4,"date":"2020-06-07T00:00:00.000Z"},{"id":6,"carID":5,"severity":3,"date":"2020-06-13T00:00:00.000Z"},{"id":7,"carID":11,"severity":2,"date":"2020-06-15T00:00:00.000Z"},{"id":8,"carID":7,"severity":1,"date":"2020-06-10T00:00:00.000Z"},{"id":9,"carID":5,"severity":3,"date":"2020-06-12T00:00:00.000Z"},{"id":10,"carID":14,"severity":2,"date":"2020-06-12T00:00:00.000Z"},{"id":11,"carID":10,"severity":5,"date":"2020-06-20T00:00:00.000Z"},{"id":12,"carID":13,"severity":2,"date":"2020-06-21T00:00:00.000Z"},{"id":13,"carID":14,"severity":5,"date":"2020-06-16T00:00:00.000Z"},{"id":14,"carID":9,"severity":5,"date":"2020-06-04T00:00:00.000Z"},{"id":15,"carID":4,"severity":3,"date":"2020-06-09T00:00:00.000Z"},{"id":16,"carID":14,"severity":4,"date":"2020-06-15T00:00:00.000Z"},{"id":17,"carID":9,"severity":5,"date":"2020-06-09T00:00:00.000Z"},{"id":18,"carID":7,"severity":5,"date":"2020-06-06T00:00:00.000Z"},{"id":19,"carID":9,"severity":1,"date":"2020-06-10T00:00:00.000Z"},{"id":20,"carID":8,"severity":1,"date":"2020-06-09T00:00:00.000Z"},{"id":21,"carID":4,"severity":3,"date":"2020-06-17T00:00:00.000Z"},{"id":22,"carID":7,"severity":3,"date":"2020-06-17T00:00:00.000Z"},{"id":23,"carID":14,"severity":3,"date":"2020-06-09T00:00:00.000Z"},{"id":24,"carID":11,"severity":3,"date":"2020-06-04T00:00:00.000Z"},{"id":25,"carID":12,"severity":3,"date":"2020-06-08T00:00:00.000Z"},{"id":26,"carID":14,"severity":5,"date":"2020-06-15T00:00:00.000Z"},{"id":27,"carID":4,"severity":4,"date":"2020-06-07T00:00:00.000Z"},{"id":28,"carID":7,"severity":4,"date":"2020-06-14T00:00:00.000Z"},{"id":29,"carID":7,"severity":5,"date":"2020-06-03T00:00:00.000Z"},{"id":30,"carID":1,"severity":1,"date":"2020-06-01T00:00:00.000Z"},{"id":31,"carID":3,"severity":1,"date":"2020-06-11T00:00:00.000Z"},{"id":32,"carID":12,"severity":2,"date":"2020-06-04T00:00:00.000Z"},{"id":33,"carID":7,"severity":2,"date":"2020-06-11T00:00:00.000Z"},{"id":34,"carID":7,"severity":1,"date":"2020-06-12T00:00:00.000Z"},{"id":35,"carID":2,"severity":4,"date":"2020-06-13T00:00:00.000Z"},{"id":36,"carID":3,"severity":2,"date":"2020-06-01T00:00:00.000Z"},{"id":37,"carID":6,"severity":2,"date":"2020-06-17T00:00:00.000Z"},{"id":38,"carID":10,"severity":4,"date":"2020-06-14T00:00:00.000Z"},{"id":39,"carID":8,"severity":1,"date":"2020-06-21T00:00:00.000Z"},{"id":40,"carID":3,"severity":4,"date":"2020-06-02T00:00:00.000Z"},{"id":41,"carID":11,"severity":2,"date":"2020-06-12T00:00:00.000Z"},{"id":42,"carID":11,"severity":2,"date":"2020-06-02T00:00:00.000Z"},{"id":43,"carID":4,"severity":2,"date":"2020-06-11T00:00:00.000Z"},{"id":44,"carID":5,"severity":1,"date":"2020-06-16T00:00:00.000Z"},{"id":45,"carID":12,"severity":3,"date":"2020-06-04T00:00:00.000Z"},{"id":46,"carID":7,"severity":2,"date":"2020-06-18T00:00:00.000Z"},{"id":47,"carID":2,"severity":3,"date":"2020-06-08T00:00:00.000Z"},{"id":48,"carID":14,"severity":1,"date":"2020-06-11T00:00:00.000Z"},{"id":49,"carID":9,"severity":5,"date":"2020-06-15T00:00:00.000Z"},{"id":50,"carID":4,"severity":1,"date":"2020-06-08T00:00:00.000Z"},{"id":51,"carID":7,"severity":3,"date":"2020-06-21T00:00:00.000Z"},{"id":52,"carID":14,"severity":2,"date":"2020-06-12T00:00:00.000Z"},{"id":53,"carID":2,"severity":2,"date":"2020-06-01T00:00:00.000Z"},{"id":54,"carID":10,"severity":5,"date":"2020-06-11T00:00:00.000Z"},{"id":55,"carID":12,"severity":5,"date":"2020-06-16T00:00:00.000Z"},{"id":56,"carID":14,"severity":1,"date":"2020-06-08T00:00:00.000Z"},{"id":57,"carID":7,"severity":5,"date":"2020-06-09T00:00:00.000Z"},{"id":58,"carID":14,"severity":5,"date":"2020-06-15T00:00:00.000Z"},{"id":59,"carID":12,"severity":3,"date":"2020-06-11T00:00:00.000Z"},{"id":60,"carID":2,"severity":1,"date":"2020-06-21T00:00:00.000Z"},{"id":61,"carID":10,"severity":5,"date":"2020-06-07T00:00:00.000Z"},{"id":62,"carID":14,"severity":1,"date":"2020-06-17T00:00:00.000Z"},{"id":63,"carID":12,"severity":5,"date":"2020-06-17T00:00:00.000Z"},{"id":64,"carID":11,"severity":4,"date":"2020-06-16T00:00:00.000Z"},{"id":65,"carID":7,"severity":4,"date":"2020-06-15T00:00:00.000Z"},{"id":66,"carID":13,"severity":4,"date":"2020-06-04T00:00:00.000Z"},{"id":67,"carID":5,"severity":2,"date":"2020-06-01T00:00:00.000Z"},{"id":68,"carID":14,"severity":3,"date":"2020-06-15T00:00:00.000Z"},{"id":69,"carID":1,"severity":2,"date":"2020-06-16T00:00:00.000Z"},{"id":70,"carID":9,"severity":3,"date":"2020-06-15T00:00:00.000Z"},{"id":71,"carID":14,"severity":4,"date":"2020-06-10T00:00:00.000Z"},{"id":72,"carID":14,"severity":4,"date":"2020-06-05T00:00:00.000Z"},{"id":73,"carID":11,"severity":2,"date":"2020-06-06T00:00:00.000Z"},{"id":74,"carID":9,"severity":4,"date":"2020-06-05T00:00:00.000Z"},{"id":75,"carID":12,"severity":1,"date":"2020-06-09T00:00:00.000Z"},{"id":76,"carID":11,"severity":4,"date":"2020-06-18T00:00:00.000Z"},{"id":77,"carID":12,"severity":3,"date":"2020-06-15T00:00:00.000Z"},{"id":78,"carID":6,"severity":5,"date":"2020-06-05T00:00:00.000Z"},{"id":79,"carID":8,"severity":1,"date":"2020-06-06T00:00:00.000Z"},{"id":80,"carID":6,"severity":5,"date":"2020-06-14T00:00:00.000Z"},{"id":81,"carID":5,"severity":2,"date":"2020-06-18T00:00:00.000Z"},{"id":82,"carID":4,"severity":1,"date":"2020-06-21T00:00:00.000Z"},{"id":83,"carID":14,"severity":1,"date":"2020-06-16T00:00:00.000Z"},{"id":84,"carID":7,"severity":4,"date":"2020-06-02T00:00:00.000Z"},{"id":85,"carID":2,"severity":4,"date":"2020-06-13T00:00:00.000Z"},{"id":86,"carID":8,"severity":5,"date":"2020-06-09T00:00:00.000Z"},{"id":87,"carID":5,"severity":4,"date":"2020-06-14T00:00:00.000Z"},{"id":88,"carID":9,"severity":4,"date":"2020-06-13T00:00:00.000Z"},{"id":89,"carID":6,"severity":4,"date":"2020-06-10T00:00:00.000Z"},{"id":90,"carID":1,"severity":4,"date":"2020-06-06T00:00:00.000Z"},{"id":91,"carID":13,"severity":3,"date":"2020-06-12T00:00:00.000Z"},{"id":92,"carID":4,"severity":3,"date":"2020-06-10T00:00:00.000Z"},{"id":93,"carID":14,"severity":1,"date":"2020-06-06T00:00:00.000Z"},{"id":94,"carID":14,"severity":5,"date":"2020-06-18T00:00:00.000Z"},{"id":95,"carID":8,"severity":5,"date":"2020-06-04T00:00:00.000Z"},{"id":96,"carID":11,"severity":1,"date":"2020-06-13T00:00:00.000Z"},{"id":97,"carID":10,"severity":5,"date":"2020-06-20T00:00:00.000Z"},{"id":98,"carID":10,"severity":2,"date":"2020-06-21T00:00:00.000Z"},{"id":99,"carID":1,"severity":1,"date":"2020-06-01T00:00:00.000Z"},{"id":100,"carID":3,"severity":5,"date":"2020-06-04T00:00:00.000Z"},{"id":101,"carID":3,"severity":3,"date":"2020-06-03T00:00:00.000Z"},{"id":102,"carID":9,"severity":3,"date":"2020-06-12T00:00:00.000Z"},{"id":103,"carID":5,"severity":1,"date":"2020-06-21T00:00:00.000Z"},{"id":104,"carID":8,"severity":4,"date":"2020-06-10T00:00:00.000Z"},{"id":105,"carID":4,"severity":1,"date":"2020-06-04T00:00:00.000Z"},{"id":106,"carID":12,"severity":4,"date":"2020-06-06T00:00:00.000Z"},{"id":107,"carID":13,"severity":5,"date":"2020-06-16T00:00:00.000Z"},{"id":108,"carID":6,"severity":2,"date":"2020-06-08T00:00:00.000Z"},{"id":109,"carID":4,"severity":5,"date":"2020-06-05T00:00:00.000Z"},{"id":110,"carID":8,"severity":2,"date":"2020-06-15T00:00:00.000Z"},{"id":111,"carID":12,"severity":1,"date":"2020-06-02T00:00:00.000Z"},{"id":112,"carID":11,"severity":3,"date":"2020-06-14T00:00:00.000Z"},{"id":113,"carID":14,"severity":2,"date":"2020-06-18T00:00:00.000Z"},{"id":114,"carID":11,"severity":4,"date":"2020-06-16T00:00:00.000Z"},{"id":115,"carID":2,"severity":3,"date":"2020-06-16T00:00:00.000Z"},{"id":116,"carID":11,"severity":3,"date":"2020-06-11T00:00:00.000Z"},{"id":117,"carID":11,"severity":3,"date":"2020-06-15T00:00:00.000Z"},{"id":118,"carID":11,"severity":3,"date":"2020-06-07T00:00:00.000Z"},{"id":119,"carID":10,"severity":2,"date":"2020-06-11T00:00:00.000Z"},{"id":120,"carID":6,"severity":4,"date":"2020-06-21T00:00:00.000Z"},{"id":121,"carID":13,"severity":5,"date":"2020-06-06T00:00:00.000Z"},{"id":122,"carID":3,"severity":5,"date":"2020-06-10T00:00:00.000Z"},{"id":123,"carID":3,"severity":2,"date":"2020-06-08T00:00:00.000Z"},{"id":124,"carID":9,"severity":3,"date":"2020-06-07T00:00:00.000Z"},{"id":125,"carID":12,"severity":1,"date":"2020-06-05T00:00:00.000Z"},{"id":126,"carID":10,"severity":5,"date":"2020-06-04T00:00:00.000Z"},{"id":127,"carID":8,"severity":4,"date":"2020-06-04T00:00:00.000Z"},{"id":128,"carID":5,"severity":1,"date":"2020-06-15T00:00:00.000Z"},{"id":129,"carID":13,"severity":1,"date":"2020-06-09T00:00:00.000Z"},{"id":130,"carID":14,"severity":3,"date":"2020-06-17T00:00:00.000Z"},{"id":131,"carID":6,"severity":2,"date":"2020-06-13T00:00:00.000Z"},{"id":132,"carID":4,"severity":4,"date":"2020-06-12T00:00:00.000Z"},{"id":133,"carID":4,"severity":4,"date":"2020-06-18T00:00:00.000Z"},{"id":134,"carID":3,"severity":1,"date":"2020-06-08T00:00:00.000Z"},{"id":135,"carID":1,"severity":1,"date":"2020-06-07T00:00:00.000Z"},{"id":136,"carID":14,"severity":3,"date":"2020-06-02T00:00:00.000Z"},{"id":137,"carID":2,"severity":4,"date":"2020-06-21T00:00:00.000Z"},{"id":138,"carID":5,"severity":2,"date":"2020-06-20T00:00:00.000Z"},{"id":139,"carID":11,"severity":2,"date":"2020-06-11T00:00:00.000Z"},{"id":140,"carID":13,"severity":1,"date":"2020-06-19T00:00:00.000Z"},{"id":141,"carID":9,"severity":5,"date":"2020-06-04T00:00:00.000Z"},{"id":142,"carID":5,"severity":1,"date":"2020-06-17T00:00:00.000Z"},{"id":143,"carID":2,"severity":5,"date":"2020-06-07T00:00:00.000Z"},{"id":144,"carID":14,"severity":5,"date":"2020-06-20T00:00:00.000Z"},{"id":145,"carID":6,"severity":4,"date":"2020-06-17T00:00:00.000Z"},{"id":146,"carID":3,"severity":4,"date":"2020-06-05T00:00:00.000Z"},{"id":147,"carID":4,"severity":4,"date":"2020-06-01T00:00:00.000Z"},{"id":148,"carID":5,"severity":2,"date":"2020-06-17T00:00:00.000Z"},{"id":149,"carID":11,"severity":2,"date":"2020-06-11T00:00:00.000Z"},{"id":150,"carID":1,"severity":2,"date":"2020-06-13T00:00:00.000Z"},{"id":151,"carID":3,"severity":4,"date":"2020-06-07T00:00:00.000Z"},{"id":152,"carID":11,"severity":1,"date":"2020-06-16T00:00:00.000Z"},{"id":153,"carID":14,"severity":3,"date":"2020-06-07T00:00:00.000Z"},{"id":154,"carID":13,"severity":1,"date":"2020-06-13T00:00:00.000Z"},{"id":155,"carID":1,"severity":5,"date":"2020-06-09T00:00:00.000Z"},{"id":156,"carID":11,"severity":3,"date":"2020-06-20T00:00:00.000Z"},{"id":157,"carID":3,"severity":1,"date":"2020-06-06T00:00:00.000Z"},{"id":158,"carID":13,"severity":2,"date":"2020-06-16T00:00:00.000Z"},{"id":159,"carID":5,"severity":1,"date":"2020-06-12T00:00:00.000Z"},{"id":160,"carID":4,"severity":4,"date":"2020-06-02T00:00:00.000Z"},{"id":161,"carID":1,"severity":1,"date":"2020-06-01T00:00:00.000Z"},{"id":162,"carID":10,"severity":4,"date":"2020-06-07T00:00:00.000Z"},{"id":163,"carID":2,"severity":5,"date":"2020-06-11T00:00:00.000Z"},{"id":164,"carID":1,"severity":4,"date":"2020-06-16T00:00:00.000Z"},{"id":165,"carID":14,"severity":5,"date":"2020-06-18T00:00:00.000Z"},{"id":166,"carID":11,"severity":3,"date":"2020-06-06T00:00:00.000Z"},{"id":167,"carID":10,"severity":2,"date":"2020-06-08T00:00:00.000Z"},{"id":168,"carID":3,"severity":5,"date":"2020-06-06T00:00:00.000Z"},{"id":169,"carID":14,"severity":1,"date":"2020-06-12T00:00:00.000Z"},{"id":170,"carID":10,"severity":5,"date":"2020-06-21T00:00:00.000Z"},{"id":171,"carID":7,"severity":4,"date":"2020-06-05T00:00:00.000Z"},{"id":172,"carID":14,"severity":2,"date":"2020-06-17T00:00:00.000Z"},{"id":173,"carID":1,"severity":1,"date":"2020-06-15T00:00:00.000Z"},{"id":174,"carID":10,"severity":3,"date":"2020-06-06T00:00:00.000Z"},{"id":175,"carID":13,"severity":4,"date":"2020-06-05T00:00:00.000Z"},{"id":176,"carID":9,"severity":4,"date":"2020-06-08T00:00:00.000Z"},{"id":177,"carID":13,"severity":4,"date":"2020-06-12T00:00:00.000Z"},{"id":178,"carID":8,"severity":4,"date":"2020-06-21T00:00:00.000Z"},{"id":179,"carID":11,"severity":5,"date":"2020-06-20T00:00:00.000Z"},{"id":180,"carID":9,"severity":1,"date":"2020-06-02T00:00:00.000Z"},{"id":181,"carID":4,"severity":2,"date":"2020-06-21T00:00:00.000Z"},{"id":182,"carID":3,"severity":2,"date":"2020-06-10T00:00:00.000Z"},{"id":183,"carID":4,"severity":4,"date":"2020-06-09T00:00:00.000Z"},{"id":184,"carID":13,"severity":4,"date":"2020-06-01T00:00:00.000Z"},{"id":185,"carID":6,"severity":3,"date":"2020-06-02T00:00:00.000Z"},{"id":186,"carID":3,"severity":2,"date":"2020-06-02T00:00:00.000Z"},{"id":187,"carID":13,"severity":4,"date":"2020-06-07T00:00:00.000Z"},{"id":188,"carID":7,"severity":3,"date":"2020-06-11T00:00:00.000Z"},{"id":189,"carID":10,"severity":5,"date":"2020-06-21T00:00:00.000Z"},{"id":190,"carID":3,"severity":4,"date":"2020-06-08T00:00:00.000Z"},{"id":191,"carID":13,"severity":2,"date":"2020-06-18T00:00:00.000Z"},{"id":192,"carID":13,"severity":3,"date":"2020-06-15T00:00:00.000Z"},{"id":193,"carID":3,"severity":5,"date":"2020-06-03T00:00:00.000Z"},{"id":194,"carID":3,"severity":4,"date":"2020-06-18T00:00:00.000Z"},{"id":195,"carID":6,"severity":2,"date":"2020-06-15T00:00:00.000Z"},{"id":196,"carID":9,"severity":1,"date":"2020-06-11T00:00:00.000Z"},{"id":197,"carID":14,"severity":1,"date":"2020-06-07T00:00:00.000Z"},{"id":198,"carID":12,"severity":3,"date":"2020-06-08T00:00:00.000Z"},{"id":199,"carID":7,"severity":4,"date":"2020-06-18T00:00:00.000Z"},{"id":200,"carID":11,"severity":1,"date":"2020-06-17T00:00:00.000Z"},{"id":201,"carID":11,"severity":4,"date":"2020-06-05T00:00:00.000Z"},{"id":202,"carID":4,"severity":4,"date":"2020-06-17T00:00:00.000Z"},{"id":203,"carID":3,"severity":5,"date":"2020-06-05T00:00:00.000Z"},{"id":204,"carID":1,"severity":1,"date":"2020-06-01T00:00:00.000Z"},{"id":205,"carID":9,"severity":2,"date":"2020-06-05T00:00:00.000Z"},{"id":206,"carID":14,"severity":4,"date":"2020-06-08T00:00:00.000Z"},{"id":207,"carID":14,"severity":3,"date":"2020-06-20T00:00:00.000Z"},{"id":208,"carID":7,"severity":1,"date":"2020-06-11T00:00:00.000Z"},{"id":209,"carID":4,"severity":1,"date":"2020-06-20T00:00:00.000Z"},{"id":210,"carID":5,"severity":4,"date":"2020-06-20T00:00:00.000Z"},{"id":211,"carID":2,"severity":5,"date":"2020-06-04T00:00:00.000Z"},{"id":212,"carID":4,"severity":5,"date":"2020-06-08T00:00:00.000Z"},{"id":213,"carID":1,"severity":3,"date":"2020-06-11T00:00:00.000Z"},{"id":214,"carID":7,"severity":5,"date":"2020-06-20T00:00:00.000Z"},{"id":215,"carID":10,"severity":3,"date":"2020-06-19T00:00:00.000Z"},{"id":216,"carID":4,"severity":1,"date":"2020-06-19T00:00:00.000Z"},{"id":217,"carID":7,"severity":1,"date":"2020-06-15T00:00:00.000Z"},{"id":218,"carID":6,"severity":1,"date":"2020-06-21T00:00:00.000Z"},{"id":219,"carID":13,"severity":3,"date":"2020-06-21T00:00:00.000Z"},{"id":220,"carID":1,"severity":3,"date":"2020-06-10T00:00:00.000Z"},{"id":221,"carID":3,"severity":4,"date":"2020-06-18T00:00:00.000Z"},{"id":222,"carID":5,"severity":1,"date":"2020-06-05T00:00:00.000Z"},{"id":223,"carID":1,"severity":3,"date":"2020-06-04T00:00:00.000Z"},{"id":224,"carID":12,"severity":4,"date":"2020-06-15T00:00:00.000Z"},{"id":225,"carID":12,"severity":5,"date":"2020-06-02T00:00:00.000Z"},{"id":226,"carID":9,"severity":2,"date":"2020-06-16T00:00:00.000Z"},{"id":227,"carID":7,"severity":1,"date":"2020-06-10T00:00:00.000Z"},{"id":228,"carID":9,"severity":4,"date":"2020-06-10T00:00:00.000Z"},{"id":229,"carID":3,"severity":1,"date":"2020-06-21T00:00:00.000Z"},{"id":230,"carID":6,"severity":1,"date":"2020-06-01T00:00:00.000Z"},{"id":231,"carID":4,"severity":1,"date":"2020-06-04T00:00:00.000Z"},{"id":232,"carID":8,"severity":1,"date":"2020-06-13T00:00:00.000Z"},{"id":233,"carID":8,"severity":3,"date":"2020-06-01T00:00:00.000Z"},{"id":234,"carID":5,"severity":4,"date":"2020-06-21T00:00:00.000Z"},{"id":235,"carID":11,"severity":5,"date":"2020-06-03T00:00:00.000Z"},{"id":236,"carID":9,"severity":1,"date":"2020-06-16T00:00:00.000Z"},{"id":237,"carID":12,"severity":3,"date":"2020-06-09T00:00:00.000Z"},{"id":238,"carID":12,"severity":5,"date":"2020-06-17T00:00:00.000Z"},{"id":239,"carID":2,"severity":3,"date":"2020-06-05T00:00:00.000Z"},{"id":240,"carID":3,"severity":2,"date":"2020-06-12T00:00:00.000Z"},{"id":241,"carID":10,"severity":2,"date":"2020-06-18T00:00:00.000Z"},{"id":242,"carID":7,"severity":3,"date":"2020-06-14T00:00:00.000Z"},{"id":243,"carID":9,"severity":2,"date":"2020-06-19T00:00:00.000Z"},{"id":244,"carID":2,"severity":5,"date":"2020-06-14T00:00:00.000Z"},{"id":245,"carID":13,"severity":4,"date":"2020-06-21T00:00:00.000Z"},{"id":246,"carID":9,"severity":2,"date":"2020-06-15T00:00:00.000Z"},{"id":247,"carID":9,"severity":4,"date":"2020-06-14T00:00:00.000Z"},{"id":248,"carID":12,"severity":3,"date":"2020-06-20T00:00:00.000Z"},{"id":249,"carID":1,"severity":1,"date":"2020-06-18T00:00:00.000Z"},{"id":250,"carID":4,"severity":5,"date":"2020-06-07T00:00:00.000Z"},{"id":251,"carID":14,"severity":2,"date":"2020-06-04T00:00:00.000Z"},{"id":252,"carID":8,"severity":3,"date":"2020-06-10T00:00:00.000Z"},{"id":253,"carID":13,"severity":2,"date":"2020-06-15T00:00:00.000Z"},{"id":254,"carID":10,"severity":2,"date":"2020-06-21T00:00:00.000Z"},{"id":255,"carID":3,"severity":1,"date":"2020-06-06T00:00:00.000Z"},{"id":256,"carID":12,"severity":5,"date":"2020-06-09T00:00:00.000Z"},{"id":257,"carID":6,"severity":5,"date":"2020-06-11T00:00:00.000Z"},{"id":258,"carID":9,"severity":2,"date":"2020-06-02T00:00:00.000Z"},{"id":259,"carID":6,"severity":5,"date":"2020-06-13T00:00:00.000Z"},{"id":260,"carID":6,"severity":5,"date":"2020-06-17T00:00:00.000Z"},{"id":261,"carID":9,"severity":1,"date":"2020-06-05T00:00:00.000Z"},{"id":262,"carID":5,"severity":5,"date":"2020-06-19T00:00:00.000Z"},{"id":263,"carID":9,"severity":5,"date":"2020-06-20T00:00:00.000Z"},{"id":264,"carID":11,"severity":4,"date":"2020-06-14T00:00:00.000Z"},{"id":265,"carID":5,"severity":2,"date":"2020-06-18T00:00:00.000Z"},{"id":266,"carID":9,"severity":2,"date":"2020-06-05T00:00:00.000Z"},{"id":267,"carID":11,"severity":5,"date":"2020-06-05T00:00:00.000Z"},{"id":268,"carID":1,"severity":4,"date":"2020-06-06T00:00:00.000Z"},{"id":269,"carID":8,"severity":2,"date":"2020-06-10T00:00:00.000Z"},{"id":270,"carID":4,"severity":5,"date":"2020-06-11T00:00:00.000Z"},{"id":271,"carID":11,"severity":5,"date":"2020-06-06T00:00:00.000Z"},{"id":272,"carID":3,"severity":2,"date":"2020-06-13T00:00:00.000Z"},{"id":273,"carID":8,"severity":1,"date":"2020-06-12T00:00:00.000Z"},{"id":274,"carID":4,"severity":3,"date":"2020-06-14T00:00:00.000Z"},{"id":275,"carID":6,"severity":4,"date":"2020-06-01T00:00:00.000Z"},{"id":276,"carID":13,"severity":3,"date":"2020-06-06T00:00:00.000Z"},{"id":277,"carID":2,"severity":1,"date":"2020-06-04T00:00:00.000Z"},{"id":278,"carID":14,"severity":1,"date":"2020-06-08T00:00:00.000Z"},{"id":279,"carID":1,"severity":4,"date":"2020-06-13T00:00:00.000Z"},{"id":280,"carID":2,"severity":4,"date":"2020-06-18T00:00:00.000Z"},{"id":281,"carID":7,"severity":1,"date":"2020-06-17T00:00:00.000Z"},{"id":282,"carID":3,"severity":1,"date":"2020-06-02T00:00:00.000Z"},{"id":283,"carID":6,"severity":1,"date":"2020-06-21T00:00:00.000Z"},{"id":284,"carID":4,"severity":3,"date":"2020-06-20T00:00:00.000Z"},{"id":285,"carID":14,"severity":5,"date":"2020-06-02T00:00:00.000Z"},{"id":286,"carID":11,"severity":2,"date":"2020-06-08T00:00:00.000Z"},{"id":287,"carID":14,"severity":5,"date":"2020-06-02T00:00:00.000Z"},{"id":288,"carID":3,"severity":4,"date":"2020-06-11T00:00:00.000Z"},{"id":289,"carID":2,"severity":4,"date":"2020-06-17T00:00:00.000Z"},{"id":290,"carID":2,"severity":2,"date":"2020-06-05T00:00:00.000Z"},{"id":291,"carID":1,"severity":5,"date":"2020-06-13T00:00:00.000Z"},{"id":292,"carID":2,"severity":4,"date":"2020-06-09T00:00:00.000Z"},{"id":293,"carID":12,"severity":3,"date":"2020-06-02T00:00:00.000Z"},{"id":294,"carID":3,"severity":5,"date":"2020-06-17T00:00:00.000Z"},{"id":295,"carID":14,"severity":3,"date":"2020-06-20T00:00:00.000Z"},{"id":296,"carID":3,"severity":2,"date":"2020-06-14T00:00:00.000Z"},{"id":297,"carID":13,"severity":1,"date":"2020-06-12T00:00:00.000Z"},{"id":298,"carID":2,"severity":2,"date":"2020-06-04T00:00:00.000Z"},{"id":299,"carID":11,"severity":2,"date":"2020-06-15T00:00:00.000Z"},{"id":300,"carID":12,"severity":1,"date":"2020-06-21T00:00:00.000Z"},{"id":301,"carID":4,"severity":3,"date":"2020-06-16T00:00:00.000Z"},{"id":302,"carID":10,"severity":1,"date":"2020-06-05T00:00:00.000Z"},{"id":303,"carID":6,"severity":1,"date":"2020-06-04T00:00:00.000Z"},{"id":304,"carID":7,"severity":4,"date":"2020-06-01T00:00:00.000Z"},{"id":305,"carID":12,"severity":5,"date":"2020-06-14T00:00:00.000Z"},{"id":306,"carID":12,"severity":2,"date":"2020-06-14T00:00:00.000Z"},{"id":307,"carID":5,"severity":5,"date":"2020-06-21T00:00:00.000Z"},{"id":308,"carID":1,"severity":5,"date":"2020-06-06T00:00:00.000Z"},{"id":309,"carID":9,"severity":3,"date":"2020-06-10T00:00:00.000Z"},{"id":310,"carID":1,"severity":3,"date":"2020-06-01T00:00:00.000Z"},{"id":311,"carID":3,"severity":2,"date":"2020-06-15T00:00:00.000Z"},{"id":312,"carID":2,"severity":1,"date":"2020-06-15T00:00:00.000Z"},{"id":313,"carID":11,"severity":4,"date":"2020-06-11T00:00:00.000Z"},{"id":314,"carID":3,"severity":2,"date":"2020-06-18T00:00:00.000Z"},{"id":315,"carID":2,"severity":4,"date":"2020-06-06T00:00:00.000Z"},{"id":316,"carID":11,"severity":2,"date":"2020-06-19T00:00:00.000Z"},{"id":317,"carID":7,"severity":5,"date":"2020-06-12T00:00:00.000Z"},{"id":318,"carID":4,"severity":3,"date":"2020-06-19T00:00:00.000Z"},{"id":319,"carID":13,"severity":1,"date":"2020-06-06T00:00:00.000Z"},{"id":320,"carID":3,"severity":5,"date":"2020-06-04T00:00:00.000Z"},{"id":321,"carID":3,"severity":1,"date":"2020-06-19T00:00:00.000Z"},{"id":322,"carID":4,"severity":1,"date":"2020-06-06T00:00:00.000Z"},{"id":323,"carID":13,"severity":5,"date":"2020-06-17T00:00:00.000Z"},{"id":324,"carID":2,"severity":3,"date":"2020-06-05T00:00:00.000Z"},{"id":325,"carID":5,"severity":3,"date":"2020-06-06T00:00:00.000Z"},{"id":326,"carID":9,"severity":3,"date":"2020-06-04T00:00:00.000Z"},{"id":327,"carID":6,"severity":1,"date":"2020-06-12T00:00:00.000Z"},{"id":328,"carID":7,"severity":1,"date":"2020-06-12T00:00:00.000Z"},{"id":329,"carID":14,"severity":4,"date":"2020-06-16T00:00:00.000Z"},{"id":330,"carID":14,"severity":4,"date":"2020-06-17T00:00:00.000Z"},{"id":331,"carID":12,"severity":3,"date":"2020-06-20T00:00:00.000Z"},{"id":332,"carID":10,"severity":1,"date":"2020-06-14T00:00:00.000Z"},{"id":333,"carID":14,"severity":3,"date":"2020-06-12T00:00:00.000Z"},{"id":334,"carID":10,"severity":3,"date":"2020-06-11T00:00:00.000Z"},{"id":335,"carID":13,"severity":2,"date":"2020-06-03T00:00:00.000Z"},{"id":336,"carID":14,"severity":4,"date":"2020-06-10T00:00:00.000Z"},{"id":337,"carID":4,"severity":1,"date":"2020-06-07T00:00:00.000Z"},{"id":338,"carID":6,"severity":3,"date":"2020-06-20T00:00:00.000Z"},{"id":339,"carID":2,"severity":2,"date":"2020-06-20T00:00:00.000Z"},{"id":340,"carID":3,"severity":1,"date":"2020-06-17T00:00:00.000Z"},{"id":341,"carID":11,"severity":5,"date":"2020-06-06T00:00:00.000Z"},{"id":342,"carID":9,"severity":1,"date":"2020-06-17T00:00:00.000Z"},{"id":343,"carID":2,"severity":3,"date":"2020-06-20T00:00:00.000Z"},{"id":344,"carID":3,"severity":2,"date":"2020-06-17T00:00:00.000Z"},{"id":345,"carID":9,"severity":5,"date":"2020-06-18T00:00:00.000Z"},{"id":346,"carID":14,"severity":2,"date":"2020-06-07T00:00:00.000Z"},{"id":347,"carID":14,"severity":1,"date":"2020-06-19T00:00:00.000Z"},{"id":348,"carID":14,"severity":3,"date":"2020-06-09T00:00:00.000Z"},{"id":349,"carID":11,"severity":4,"date":"2020-06-16T00:00:00.000Z"},{"id":350,"carID":6,"severity":4,"date":"2020-06-11T00:00:00.000Z"},{"id":351,"carID":14,"severity":3,"date":"2020-06-07T00:00:00.000Z"},{"id":352,"carID":10,"severity":3,"date":"2020-06-19T00:00:00.000Z"},{"id":353,"carID":13,"severity":2,"date":"2020-06-15T00:00:00.000Z"},{"id":354,"carID":3,"severity":2,"date":"2020-06-10T00:00:00.000Z"},{"id":355,"carID":7,"severity":5,"date":"2020-06-10T00:00:00.000Z"},{"id":356,"carID":8,"severity":5,"date":"2020-06-16T00:00:00.000Z"},{"id":357,"carID":9,"severity":3,"date":"2020-06-19T00:00:00.000Z"},{"id":358,"carID":4,"severity":1,"date":"2020-06-12T00:00:00.000Z"},{"id":359,"carID":4,"severity":4,"date":"2020-06-13T00:00:00.000Z"},{"id":360,"carID":14,"severity":5,"date":"2020-06-15T00:00:00.000Z"},{"id":361,"carID":13,"severity":3,"date":"2020-06-05T00:00:00.000Z"},{"id":362,"carID":4,"severity":3,"date":"2020-06-04T00:00:00.000Z"},{"id":363,"carID":6,"severity":1,"date":"2020-06-08T00:00:00.000Z"},{"id":364,"carID":5,"severity":4,"date":"2020-06-06T00:00:00.000Z"},{"id":365,"carID":9,"severity":4,"date":"2020-06-01T00:00:00.000Z"},{"id":366,"carID":9,"severity":1,"date":"2020-06-04T00:00:00.000Z"},{"id":367,"carID":14,"severity":5,"date":"2020-06-14T00:00:00.000Z"},{"id":368,"carID":12,"severity":3,"date":"2020-06-20T00:00:00.000Z"},{"id":369,"carID":13,"severity":2,"date":"2020-06-09T00:00:00.000Z"},{"id":370,"carID":14,"severity":3,"date":"2020-06-07T00:00:00.000Z"},{"id":371,"carID":10,"severity":4,"date":"2020-06-06T00:00:00.000Z"},{"id":372,"carID":13,"severity":3,"date":"2020-06-13T00:00:00.000Z"},{"id":373,"carID":7,"severity":4,"date":"2020-06-12T00:00:00.000Z"},{"id":374,"carID":3,"severity":3,"date":"2020-06-18T00:00:00.000Z"},{"id":375,"carID":12,"severity":1,"date":"2020-06-01T00:00:00.000Z"},{"id":376,"carID":13,"severity":3,"date":"2020-06-18T00:00:00.000Z"},{"id":377,"carID":9,"severity":2,"date":"2020-06-13T00:00:00.000Z"},{"id":378,"carID":14,"severity":3,"date":"2020-06-10T00:00:00.000Z"},{"id":379,"carID":10,"severity":2,"date":"2020-06-08T00:00:00.000Z"},{"id":380,"carID":7,"severity":1,"date":"2020-06-13T00:00:00.000Z"},{"id":381,"carID":13,"severity":3,"date":"2020-06-21T00:00:00.000Z"},{"id":382,"carID":8,"severity":3,"date":"2020-06-15T00:00:00.000Z"},{"id":383,"carID":14,"severity":2,"date":"2020-06-17T00:00:00.000Z"},{"id":384,"carID":1,"severity":5,"date":"2020-06-09T00:00:00.000Z"},{"id":385,"carID":5,"severity":1,"date":"2020-06-03T00:00:00.000Z"},{"id":386,"carID":3,"severity":4,"date":"2020-06-12T00:00:00.000Z"},{"id":387,"carID":12,"severity":5,"date":"2020-06-12T00:00:00.000Z"},{"id":388,"carID":7,"severity":2,"date":"2020-06-02T00:00:00.000Z"},{"id":389,"carID":7,"severity":2,"date":"2020-06-18T00:00:00.000Z"},{"id":390,"carID":1,"severity":3,"date":"2020-06-05T00:00:00.000Z"},{"id":391,"carID":4,"severity":3,"date":"2020-06-03T00:00:00.000Z"},{"id":392,"carID":5,"severity":3,"date":"2020-06-15T00:00:00.000Z"},{"id":393,"carID":3,"severity":2,"date":"2020-06-13T00:00:00.000Z"},{"id":394,"carID":5,"severity":1,"date":"2020-06-20T00:00:00.000Z"},{"id":395,"carID":3,"severity":4,"date":"2020-06-09T00:00:00.000Z"},{"id":396,"carID":6,"severity":4,"date":"2020-06-03T00:00:00.000Z"},{"id":397,"carID":12,"severity":3,"date":"2020-06-12T00:00:00.000Z"},{"id":398,"carID":5,"severity":2,"date":"2020-06-10T00:00:00.000Z"},{"id":399,"carID":8,"severity":5,"date":"2020-06-05T00:00:00.000Z"},{"id":400,"carID":5,"severity":3,"date":"2020-06-02T00:00:00.000Z"},{"id":401,"carID":11,"severity":1,"date":"2020-06-18T00:00:00.000Z"},{"id":402,"carID":10,"severity":4,"date":"2020-06-20T00:00:00.000Z"},{"id":403,"carID":13,"severity":1,"date":"2020-06-17T00:00:00.000Z"},{"id":404,"carID":8,"severity":2,"date":"2020-06-01T00:00:00.000Z"},{"id":405,"carID":14,"severity":5,"date":"2020-06-20T00:00:00.000Z"},{"id":406,"carID":13,"severity":2,"date":"2020-06-13T00:00:00.000Z"},{"id":407,"carID":9,"severity":1,"date":"2020-06-15T00:00:00.000Z"},{"id":408,"carID":12,"severity":1,"date":"2020-06-13T00:00:00.000Z"},{"id":409,"carID":10,"severity":3,"date":"2020-06-15T00:00:00.000Z"},{"id":410,"carID":1,"severity":4,"date":"2020-06-10T00:00:00.000Z"},{"id":411,"carID":13,"severity":2,"date":"2020-06-15T00:00:00.000Z"},{"id":412,"carID":14,"severity":2,"date":"2020-06-06T00:00:00.000Z"},{"id":413,"carID":5,"severity":4,"date":"2020-06-04T00:00:00.000Z"},{"id":414,"carID":11,"severity":5,"date":"2020-06-18T00:00:00.000Z"},{"id":415,"carID":12,"severity":4,"date":"2020-06-21T00:00:00.000Z"},{"id":416,"carID":13,"severity":1,"date":"2020-06-15T00:00:00.000Z"},{"id":417,"carID":6,"severity":3,"date":"2020-06-18T00:00:00.000Z"},{"id":418,"carID":14,"severity":2,"date":"2020-06-21T00:00:00.000Z"},{"id":419,"carID":6,"severity":1,"date":"2020-06-10T00:00:00.000Z"},{"id":420,"carID":4,"severity":1,"date":"2020-06-20T00:00:00.000Z"},{"id":421,"carID":4,"severity":4,"date":"2020-06-19T00:00:00.000Z"},{"id":422,"carID":13,"severity":1,"date":"2020-06-04T00:00:00.000Z"},{"id":423,"carID":7,"severity":1,"date":"2020-06-09T00:00:00.000Z"},{"id":424,"carID":8,"severity":5,"date":"2020-06-12T00:00:00.000Z"},{"id":425,"carID":6,"severity":3,"date":"2020-06-14T00:00:00.000Z"},{"id":426,"carID":9,"severity":1,"date":"2020-06-09T00:00:00.000Z"},{"id":427,"carID":13,"severity":5,"date":"2020-06-19T00:00:00.000Z"},{"id":428,"carID":4,"severity":5,"date":"2020-06-16T00:00:00.000Z"},{"id":429,"carID":6,"severity":1,"date":"2020-06-05T00:00:00.000Z"},{"id":430,"carID":7,"severity":5,"date":"2020-06-16T00:00:00.000Z"},{"id":431,"carID":11,"severity":2,"date":"2020-06-02T00:00:00.000Z"},{"id":432,"carID":2,"severity":4,"date":"2020-06-05T00:00:00.000Z"},{"id":433,"carID":12,"severity":3,"date":"2020-06-19T00:00:00.000Z"},{"id":434,"carID":10,"severity":1,"date":"2020-06-02T00:00:00.000Z"},{"id":435,"carID":11,"severity":2,"date":"2020-06-04T00:00:00.000Z"},{"id":436,"carID":8,"severity":3,"date":"2020-06-13T00:00:00.000Z"},{"id":437,"carID":10,"severity":3,"date":"2020-06-20T00:00:00.000Z"},{"id":438,"carID":5,"severity":3,"date":"2020-06-17T00:00:00.000Z"},{"id":439,"carID":14,"severity":5,"date":"2020-06-19T00:00:00.000Z"},{"id":440,"carID":6,"severity":2,"date":"2020-06-09T00:00:00.000Z"},{"id":441,"carID":12,"severity":3,"date":"2020-06-20T00:00:00.000Z"},{"id":442,"carID":2,"severity":1,"date":"2020-06-07T00:00:00.000Z"},{"id":443,"carID":9,"severity":4,"date":"2020-06-13T00:00:00.000Z"},{"id":444,"carID":1,"severity":4,"date":"2020-06-17T00:00:00.000Z"},{"id":445,"carID":8,"severity":5,"date":"2020-06-17T00:00:00.000Z"},{"id":446,"carID":2,"severity":5,"date":"2020-06-19T00:00:00.000Z"},{"id":447,"carID":4,"severity":1,"date":"2020-06-08T00:00:00.000Z"},{"id":448,"carID":1,"severity":1,"date":"2020-06-15T00:00:00.000Z"},{"id":449,"carID":8,"severity":4,"date":"2020-06-11T00:00:00.000Z"},{"id":450,"carID":7,"severity":5,"date":"2020-06-21T00:00:00.000Z"},{"id":451,"carID":14,"severity":4,"date":"2020-06-10T00:00:00.000Z"},{"id":452,"carID":5,"severity":5,"date":"2020-06-14T00:00:00.000Z"},{"id":453,"carID":9,"severity":3,"date":"2020-06-02T00:00:00.000Z"},{"id":454,"carID":7,"severity":4,"date":"2020-06-14T00:00:00.000Z"},{"id":455,"carID":7,"severity":2,"date":"2020-06-09T00:00:00.000Z"},{"id":456,"carID":4,"severity":1,"date":"2020-06-18T00:00:00.000Z"},{"id":457,"carID":4,"severity":2,"date":"2020-06-16T00:00:00.000Z"},{"id":458,"carID":5,"severity":3,"date":"2020-06-16T00:00:00.000Z"},{"id":459,"carID":1,"severity":3,"date":"2020-06-06T00:00:00.000Z"},{"id":460,"carID":5,"severity":5,"date":"2020-06-19T00:00:00.000Z"},{"id":461,"carID":11,"severity":2,"date":"2020-06-06T00:00:00.000Z"},{"id":462,"carID":7,"severity":1,"date":"2020-06-11T00:00:00.000Z"},{"id":463,"carID":2,"severity":5,"date":"2020-06-06T00:00:00.000Z"},{"id":464,"carID":6,"severity":3,"date":"2020-06-20T00:00:00.000Z"},{"id":465,"carID":3,"severity":4,"date":"2020-06-13T00:00:00.000Z"},{"id":466,"carID":14,"severity":2,"date":"2020-06-12T00:00:00.000Z"},{"id":467,"carID":11,"severity":5,"date":"2020-06-18T00:00:00.000Z"},{"id":468,"carID":4,"severity":1,"date":"2020-06-09T00:00:00.000Z"},{"id":469,"carID":6,"severity":5,"date":"2020-06-03T00:00:00.000Z"},{"id":470,"carID":12,"severity":3,"date":"2020-06-03T00:00:00.000Z"},{"id":471,"carID":8,"severity":3,"date":"2020-06-09T00:00:00.000Z"},{"id":472,"carID":3,"severity":2,"date":"2020-06-04T00:00:00.000Z"},{"id":473,"carID":10,"severity":2,"date":"2020-06-14T00:00:00.000Z"},{"id":474,"carID":10,"severity":1,"date":"2020-06-02T00:00:00.000Z"},{"id":475,"carID":9,"severity":5,"date":"2020-06-21T00:00:00.000Z"},{"id":476,"carID":6,"severity":5,"date":"2020-06-19T00:00:00.000Z"},{"id":477,"carID":3,"severity":4,"date":"2020-06-05T00:00:00.000Z"},{"id":478,"carID":14,"severity":2,"date":"2020-06-04T00:00:00.000Z"},{"id":479,"carID":14,"severity":5,"date":"2020-06-09T00:00:00.000Z"},{"id":480,"carID":11,"severity":5,"date":"2020-06-15T00:00:00.000Z"},{"id":481,"carID":14,"severity":4,"date":"2020-06-03T00:00:00.000Z"},{"id":482,"carID":5,"severity":5,"date":"2020-06-07T00:00:00.000Z"},{"id":483,"carID":10,"severity":5,"date":"2020-06-12T00:00:00.000Z"},{"id":484,"carID":12,"severity":5,"date":"2020-06-11T00:00:00.000Z"},{"id":485,"carID":2,"severity":2,"date":"2020-06-05T00:00:00.000Z"},{"id":486,"carID":12,"severity":3,"date":"2020-06-19T00:00:00.000Z"},{"id":487,"carID":7,"severity":2,"date":"2020-06-21T00:00:00.000Z"},{"id":488,"carID":1,"severity":5,"date":"2020-06-18T00:00:00.000Z"},{"id":489,"carID":3,"severity":5,"date":"2020-06-18T00:00:00.000Z"},{"id":490,"carID":7,"severity":3,"date":"2020-06-03T00:00:00.000Z"},{"id":491,"carID":10,"severity":3,"date":"2020-06-17T00:00:00.000Z"},{"id":492,"carID":12,"severity":3,"date":"2020-06-09T00:00:00.000Z"},{"id":493,"carID":12,"severity":4,"date":"2020-06-11T00:00:00.000Z"},{"id":494,"carID":3,"severity":5,"date":"2020-06-01T00:00:00.000Z"},{"id":495,"carID":7,"severity":3,"date":"2020-06-16T00:00:00.000Z"},{"id":496,"carID":13,"severity":2,"date":"2020-06-01T00:00:00.000Z"},{"id":497,"carID":8,"severity":3,"date":"2020-06-21T00:00:00.000Z"},{"id":498,"carID":10,"severity":5,"date":"2020-06-13T00:00:00.000Z"},{"id":499,"carID":14,"severity":1,"date":"2020-06-16T00:00:00.000Z"},{"id":500,"carID":9,"severity":3,"date":"2020-06-13T00:00:00.000Z"},{"id":501,"carID":3,"severity":4,"date":"2020-06-04T00:00:00.000Z"},{"id":502,"carID":13,"severity":4,"date":"2020-06-14T00:00:00.000Z"},{"id":503,"carID":5,"severity":4,"date":"2020-06-07T00:00:00.000Z"},{"id":504,"carID":3,"severity":1,"date":"2020-06-09T00:00:00.000Z"},{"id":505,"carID":4,"severity":4,"date":"2020-06-14T00:00:00.000Z"},{"id":506,"carID":5,"severity":3,"date":"2020-06-07T00:00:00.000Z"},{"id":507,"carID":3,"severity":1,"date":"2020-06-17T00:00:00.000Z"},{"id":508,"carID":6,"severity":3,"date":"2020-06-09T00:00:00.000Z"},{"id":509,"carID":12,"severity":5,"date":"2020-06-09T00:00:00.000Z"},{"id":510,"carID":5,"severity":5,"date":"2020-06-06T00:00:00.000Z"},{"id":511,"carID":14,"severity":1,"date":"2020-06-12T00:00:00.000Z"},{"id":512,"carID":14,"severity":4,"date":"2020-06-14T00:00:00.000Z"},{"id":513,"carID":4,"severity":3,"date":"2020-06-20T00:00:00.000Z"},{"id":514,"carID":11,"severity":4,"date":"2020-06-01T00:00:00.000Z"},{"id":515,"carID":13,"severity":3,"date":"2020-06-21T00:00:00.000Z"},{"id":516,"carID":1,"severity":3,"date":"2020-06-17T00:00:00.000Z"},{"id":517,"carID":3,"severity":1,"date":"2020-06-05T00:00:00.000Z"},{"id":518,"carID":11,"severity":4,"date":"2020-06-01T00:00:00.000Z"},{"id":519,"carID":12,"severity":1,"date":"2020-06-05T00:00:00.000Z"},{"id":520,"carID":9,"severity":1,"date":"2020-06-03T00:00:00.000Z"},{"id":521,"carID":3,"severity":4,"date":"2020-06-05T00:00:00.000Z"},{"id":522,"carID":14,"severity":5,"date":"2020-06-12T00:00:00.000Z"},{"id":523,"carID":6,"severity":4,"date":"2020-06-04T00:00:00.000Z"},{"id":524,"carID":4,"severity":2,"date":"2020-06-06T00:00:00.000Z"},{"id":525,"carID":3,"severity":1,"date":"2020-06-11T00:00:00.000Z"},{"id":526,"carID":4,"severity":1,"date":"2020-06-06T00:00:00.000Z"},{"id":527,"carID":9,"severity":2,"date":"2020-06-14T00:00:00.000Z"},{"id":528,"carID":9,"severity":1,"date":"2020-06-11T00:00:00.000Z"},{"id":529,"carID":1,"severity":2,"date":"2020-06-19T00:00:00.000Z"},{"id":530,"carID":12,"severity":5,"date":"2020-06-21T00:00:00.000Z"},{"id":531,"carID":7,"severity":1,"date":"2020-06-10T00:00:00.000Z"},{"id":532,"carID":7,"severity":5,"date":"2020-06-03T00:00:00.000Z"},{"id":533,"carID":11,"severity":2,"date":"2020-06-09T00:00:00.000Z"},{"id":534,"carID":7,"severity":3,"date":"2020-06-05T00:00:00.000Z"},{"id":535,"carID":10,"severity":2,"date":"2020-06-05T00:00:00.000Z"},{"id":536,"carID":4,"severity":2,"date":"2020-06-18T00:00:00.000Z"},{"id":537,"carID":7,"severity":1,"date":"2020-06-06T00:00:00.000Z"},{"id":538,"carID":4,"severity":5,"date":"2020-06-10T00:00:00.000Z"},{"id":539,"carID":13,"severity":1,"date":"2020-06-21T00:00:00.000Z"},{"id":540,"carID":1,"severity":5,"date":"2020-06-14T00:00:00.000Z"},{"id":541,"carID":8,"severity":5,"date":"2020-06-15T00:00:00.000Z"},{"id":542,"carID":4,"severity":4,"date":"2020-06-09T00:00:00.000Z"},{"id":543,"carID":1,"severity":3,"date":"2020-06-05T00:00:00.000Z"},{"id":544,"carID":5,"severity":4,"date":"2020-06-10T00:00:00.000Z"},{"id":545,"carID":4,"severity":1,"date":"2020-06-14T00:00:00.000Z"},{"id":546,"carID":2,"severity":3,"date":"2020-06-07T00:00:00.000Z"},{"id":547,"carID":7,"severity":2,"date":"2020-06-09T00:00:00.000Z"},{"id":548,"carID":2,"severity":5,"date":"2020-06-08T00:00:00.000Z"},{"id":549,"carID":6,"severity":5,"date":"2020-06-15T00:00:00.000Z"},{"id":550,"carID":1,"severity":2,"date":"2020-06-04T00:00:00.000Z"},{"id":551,"carID":3,"severity":2,"date":"2020-06-17T00:00:00.000Z"},{"id":552,"carID":9,"severity":1,"date":"2020-06-15T00:00:00.000Z"},{"id":553,"carID":9,"severity":1,"date":"2020-06-17T00:00:00.000Z"},{"id":554,"carID":4,"severity":5,"date":"2020-06-15T00:00:00.000Z"},{"id":555,"carID":8,"severity":2,"date":"2020-06-19T00:00:00.000Z"},{"id":556,"carID":8,"severity":3,"date":"2020-06-12T00:00:00.000Z"},{"id":557,"carID":9,"severity":5,"date":"2020-06-17T00:00:00.000Z"},{"id":558,"carID":5,"severity":5,"date":"2020-06-07T00:00:00.000Z"},{"id":559,"carID":11,"severity":4,"date":"2020-06-18T00:00:00.000Z"},{"id":560,"carID":2,"severity":5,"date":"2020-06-18T00:00:00.000Z"},{"id":561,"carID":3,"severity":3,"date":"2020-06-13T00:00:00.000Z"},{"id":562,"carID":12,"severity":2,"date":"2020-06-05T00:00:00.000Z"},{"id":563,"carID":6,"severity":5,"date":"2020-06-04T00:00:00.000Z"},{"id":564,"carID":5,"severity":5,"date":"2020-06-10T00:00:00.000Z"},{"id":565,"carID":1,"severity":5,"date":"2020-06-03T00:00:00.000Z"},{"id":566,"carID":1,"severity":3,"date":"2020-06-06T00:00:00.000Z"},{"id":567,"carID":3,"severity":5,"date":"2020-06-16T00:00:00.000Z"},{"id":568,"carID":9,"severity":1,"date":"2020-06-01T00:00:00.000Z"},{"id":569,"carID":14,"severity":5,"date":"2020-06-20T00:00:00.000Z"},{"id":570,"carID":3,"severity":1,"date":"2020-06-18T00:00:00.000Z"},{"id":571,"carID":1,"severity":1,"date":"2020-06-13T00:00:00.000Z"},{"id":572,"carID":11,"severity":3,"date":"2020-06-19T00:00:00.000Z"},{"id":573,"carID":6,"severity":1,"date":"2020-06-09T00:00:00.000Z"},{"id":574,"carID":6,"severity":5,"date":"2020-06-12T00:00:00.000Z"},{"id":575,"carID":7,"severity":4,"date":"2020-06-11T00:00:00.000Z"},{"id":576,"carID":11,"severity":5,"date":"2020-06-09T00:00:00.000Z"},{"id":577,"carID":14,"severity":4,"date":"2020-06-04T00:00:00.000Z"},{"id":578,"carID":8,"severity":1,"date":"2020-06-19T00:00:00.000Z"},{"id":579,"carID":4,"severity":4,"date":"2020-06-18T00:00:00.000Z"},{"id":580,"carID":10,"severity":3,"date":"2020-06-20T00:00:00.000Z"},{"id":581,"carID":1,"severity":2,"date":"2020-06-13T00:00:00.000Z"},{"id":582,"carID":12,"severity":2,"date":"2020-06-15T00:00:00.000Z"},{"id":583,"carID":12,"severity":2,"date":"2020-06-04T00:00:00.000Z"},{"id":584,"carID":4,"severity":3,"date":"2020-06-14T00:00:00.000Z"},{"id":585,"carID":14,"severity":4,"date":"2020-06-03T00:00:00.000Z"},{"id":586,"carID":14,"severity":5,"date":"2020-06-05T00:00:00.000Z"},{"id":587,"carID":8,"severity":3,"date":"2020-06-06T00:00:00.000Z"},{"id":588,"carID":1,"severity":3,"date":"2020-06-02T00:00:00.000Z"},{"id":589,"carID":11,"severity":5,"date":"2020-06-04T00:00:00.000Z"},{"id":590,"carID":6,"severity":5,"date":"2020-06-13T00:00:00.000Z"},{"id":591,"carID":14,"severity":4,"date":"2020-06-08T00:00:00.000Z"},{"id":592,"carID":7,"severity":5,"date":"2020-06-06T00:00:00.000Z"},{"id":593,"carID":8,"severity":1,"date":"2020-06-09T00:00:00.000Z"},{"id":594,"carID":2,"severity":3,"date":"2020-06-12T00:00:00.000Z"},{"id":595,"carID":3,"severity":2,"date":"2020-06-13T00:00:00.000Z"},{"id":596,"carID":9,"severity":3,"date":"2020-06-19T00:00:00.000Z"},{"id":597,"carID":4,"severity":4,"date":"2020-06-19T00:00:00.000Z"},{"id":598,"carID":3,"severity":5,"date":"2020-06-21T00:00:00.000Z"},{"id":599,"carID":13,"severity":4,"date":"2020-06-15T00:00:00.000Z"},{"id":600,"carID":11,"severity":2,"date":"2020-06-05T00:00:00.000Z"},{"id":601,"carID":7,"severity":4,"date":"2020-06-07T00:00:00.000Z"},{"id":602,"carID":2,"severity":1,"date":"2020-06-12T00:00:00.000Z"},{"id":603,"carID":10,"severity":3,"date":"2020-06-14T00:00:00.000Z"},{"id":604,"carID":2,"severity":5,"date":"2020-06-19T00:00:00.000Z"},{"id":605,"carID":11,"severity":5,"date":"2020-06-04T00:00:00.000Z"},{"id":606,"carID":13,"severity":4,"date":"2020-06-12T00:00:00.000Z"},{"id":607,"carID":14,"severity":5,"date":"2020-06-16T00:00:00.000Z"},{"id":608,"carID":4,"severity":4,"date":"2020-06-08T00:00:00.000Z"},{"id":609,"carID":11,"severity":1,"date":"2020-06-18T00:00:00.000Z"},{"id":610,"carID":8,"severity":2,"date":"2020-06-12T00:00:00.000Z"},{"id":611,"carID":3,"severity":4,"date":"2020-06-08T00:00:00.000Z"},{"id":612,"carID":11,"severity":2,"date":"2020-06-03T00:00:00.000Z"},{"id":613,"carID":6,"severity":2,"date":"2020-06-17T00:00:00.000Z"},{"id":614,"carID":4,"severity":5,"date":"2020-06-07T00:00:00.000Z"},{"id":615,"carID":2,"severity":2,"date":"2020-06-12T00:00:00.000Z"},{"id":616,"carID":14,"severity":3,"date":"2020-06-03T00:00:00.000Z"},{"id":617,"carID":6,"severity":2,"date":"2020-06-03T00:00:00.000Z"},{"id":618,"carID":6,"severity":1,"date":"2020-06-12T00:00:00.000Z"},{"id":619,"carID":13,"severity":4,"date":"2020-06-09T00:00:00.000Z"},{"id":620,"carID":11,"severity":5,"date":"2020-06-05T00:00:00.000Z"},{"id":621,"carID":14,"severity":3,"date":"2020-06-07T00:00:00.000Z"},{"id":622,"carID":3,"severity":5,"date":"2020-06-13T00:00:00.000Z"},{"id":623,"carID":12,"severity":4,"date":"2020-06-14T00:00:00.000Z"},{"id":624,"carID":12,"severity":2,"date":"2020-06-21T00:00:00.000Z"},{"id":625,"carID":2,"severity":3,"date":"2020-06-14T00:00:00.000Z"},{"id":626,"carID":7,"severity":4,"date":"2020-06-13T00:00:00.000Z"},{"id":627,"carID":8,"severity":1,"date":"2020-06-06T00:00:00.000Z"},{"id":628,"carID":2,"severity":3,"date":"2020-06-09T00:00:00.000Z"},{"id":629,"carID":2,"severity":2,"date":"2020-06-19T00:00:00.000Z"},{"id":630,"carID":5,"severity":4,"date":"2020-06-19T00:00:00.000Z"},{"id":631,"carID":11,"severity":2,"date":"2020-06-15T00:00:00.000Z"},{"id":632,"carID":11,"severity":1,"date":"2020-06-13T00:00:00.000Z"},{"id":633,"carID":2,"severity":2,"date":"2020-06-08T00:00:00.000Z"},{"id":634,"carID":4,"severity":2,"date":"2020-06-18T00:00:00.000Z"},{"id":635,"carID":14,"severity":4,"date":"2020-06-09T00:00:00.000Z"},{"id":636,"carID":1,"severity":2,"date":"2020-06-11T00:00:00.000Z"},{"id":637,"carID":10,"severity":1,"date":"2020-06-03T00:00:00.000Z"},{"id":638,"carID":3,"severity":1,"date":"2020-06-21T00:00:00.000Z"},{"id":639,"carID":9,"severity":2,"date":"2020-06-10T00:00:00.000Z"},{"id":640,"carID":11,"severity":5,"date":"2020-06-19T00:00:00.000Z"},{"id":641,"carID":14,"severity":4,"date":"2020-06-08T00:00:00.000Z"},{"id":642,"carID":14,"severity":1,"date":"2020-06-08T00:00:00.000Z"},{"id":643,"carID":1,"severity":3,"date":"2020-06-16T00:00:00.000Z"},{"id":644,"carID":4,"severity":4,"date":"2020-06-11T00:00:00.000Z"},{"id":645,"carID":7,"severity":3,"date":"2020-06-02T00:00:00.000Z"},{"id":646,"carID":9,"severity":5,"date":"2020-06-05T00:00:00.000Z"},{"id":647,"carID":10,"severity":2,"date":"2020-06-10T00:00:00.000Z"},{"id":648,"carID":3,"severity":3,"date":"2020-06-04T00:00:00.000Z"},{"id":649,"carID":6,"severity":3,"date":"2020-06-20T00:00:00.000Z"},{"id":650,"carID":14,"severity":1,"date":"2020-06-09T00:00:00.000Z"},{"id":651,"carID":11,"severity":1,"date":"2020-06-20T00:00:00.000Z"},{"id":652,"carID":8,"severity":1,"date":"2020-06-18T00:00:00.000Z"},{"id":653,"carID":3,"severity":3,"date":"2020-06-17T00:00:00.000Z"},{"id":654,"carID":9,"severity":5,"date":"2020-06-16T00:00:00.000Z"},{"id":655,"carID":14,"severity":5,"date":"2020-06-15T00:00:00.000Z"},{"id":656,"carID":10,"severity":3,"date":"2020-06-09T00:00:00.000Z"},{"id":657,"carID":11,"severity":5,"date":"2020-06-04T00:00:00.000Z"},{"id":658,"carID":3,"severity":5,"date":"2020-06-11T00:00:00.000Z"},{"id":659,"carID":12,"severity":5,"date":"2020-06-02T00:00:00.000Z"},{"id":660,"carID":13,"severity":5,"date":"2020-06-13T00:00:00.000Z"},{"id":661,"carID":5,"severity":1,"date":"2020-06-16T00:00:00.000Z"},{"id":662,"carID":2,"severity":1,"date":"2020-06-17T00:00:00.000Z"},{"id":663,"carID":14,"severity":4,"date":"2020-06-15T00:00:00.000Z"},{"id":664,"carID":11,"severity":5,"date":"2020-06-14T00:00:00.000Z"},{"id":665,"carID":11,"severity":4,"date":"2020-06-18T00:00:00.000Z"},{"id":666,"carID":6,"severity":4,"date":"2020-06-13T00:00:00.000Z"},{"id":667,"carID":7,"severity":4,"date":"2020-06-02T00:00:00.000Z"},{"id":668,"carID":14,"severity":2,"date":"2020-06-15T00:00:00.000Z"},{"id":669,"carID":14,"severity":3,"date":"2020-06-16T00:00:00.000Z"},{"id":670,"carID":4,"severity":4,"date":"2020-06-05T00:00:00.000Z"},{"id":671,"carID":14,"severity":2,"date":"2020-06-12T00:00:00.000Z"},{"id":672,"carID":5,"severity":1,"date":"2020-06-13T00:00:00.000Z"},{"id":673,"carID":7,"severity":5,"date":"2020-06-09T00:00:00.000Z"},{"id":674,"carID":14,"severity":1,"date":"2020-06-07T00:00:00.000Z"},{"id":675,"carID":1,"severity":4,"date":"2020-06-20T00:00:00.000Z"},{"id":676,"carID":11,"severity":4,"date":"2020-06-06T00:00:00.000Z"},{"id":677,"carID":10,"severity":2,"date":"2020-06-06T00:00:00.000Z"},{"id":678,"carID":9,"severity":2,"date":"2020-06-07T00:00:00.000Z"},{"id":679,"carID":13,"severity":5,"date":"2020-06-18T00:00:00.000Z"},{"id":680,"carID":11,"severity":2,"date":"2020-06-11T00:00:00.000Z"},{"id":681,"carID":5,"severity":4,"date":"2020-06-09T00:00:00.000Z"},{"id":682,"carID":6,"severity":5,"date":"2020-06-04T00:00:00.000Z"},{"id":683,"carID":6,"severity":4,"date":"2020-06-10T00:00:00.000Z"},{"id":684,"carID":11,"severity":3,"date":"2020-06-09T00:00:00.000Z"},{"id":685,"carID":3,"severity":4,"date":"2020-06-13T00:00:00.000Z"},{"id":686,"carID":10,"severity":1,"date":"2020-06-09T00:00:00.000Z"},{"id":687,"carID":1,"severity":1,"date":"2020-06-17T00:00:00.000Z"},{"id":688,"carID":1,"severity":3,"date":"2020-06-16T00:00:00.000Z"},{"id":689,"carID":11,"severity":3,"date":"2020-06-13T00:00:00.000Z"},{"id":690,"carID":1,"severity":5,"date":"2020-06-12T00:00:00.000Z"},{"id":691,"carID":8,"severity":4,"date":"2020-06-10T00:00:00.000Z"},{"id":692,"carID":11,"severity":2,"date":"2020-06-10T00:00:00.000Z"},{"id":693,"carID":9,"severity":5,"date":"2020-06-02T00:00:00.000Z"},{"id":694,"carID":10,"severity":5,"date":"2020-06-18T00:00:00.000Z"},{"id":695,"carID":7,"severity":3,"date":"2020-06-17T00:00:00.000Z"},{"id":696,"carID":12,"severity":5,"date":"2020-06-10T00:00:00.000Z"},{"id":697,"carID":6,"severity":1,"date":"2020-06-14T00:00:00.000Z"},{"id":698,"carID":12,"severity":5,"date":"2020-06-01T00:00:00.000Z"},{"id":699,"carID":8,"severity":3,"date":"2020-06-08T00:00:00.000Z"},{"id":700,"carID":1,"severity":4,"date":"2020-06-13T00:00:00.000Z"},{"id":701,"carID":9,"severity":5,"date":"2020-06-17T00:00:00.000Z"},{"id":702,"carID":14,"severity":1,"date":"2020-06-13T00:00:00.000Z"},{"id":703,"carID":2,"severity":5,"date":"2020-06-12T00:00:00.000Z"},{"id":704,"carID":14,"severity":5,"date":"2020-06-16T00:00:00.000Z"},{"id":705,"carID":2,"severity":4,"date":"2020-06-07T00:00:00.000Z"},{"id":706,"carID":10,"severity":3,"date":"2020-06-07T00:00:00.000Z"},{"id":707,"carID":8,"severity":2,"date":"2020-06-06T00:00:00.000Z"},{"id":708,"carID":13,"severity":3,"date":"2020-06-13T00:00:00.000Z"},{"id":709,"carID":3,"severity":5,"date":"2020-06-07T00:00:00.000Z"},{"id":710,"carID":5,"severity":4,"date":"2020-06-12T00:00:00.000Z"},{"id":711,"carID":14,"severity":3,"date":"2020-06-02T00:00:00.000Z"},{"id":712,"carID":2,"severity":4,"date":"2020-06-07T00:00:00.000Z"},{"id":713,"carID":5,"severity":1,"date":"2020-06-07T00:00:00.000Z"},{"id":714,"carID":9,"severity":1,"date":"2020-06-07T00:00:00.000Z"},{"id":715,"carID":14,"severity":4,"date":"2020-06-19T00:00:00.000Z"},{"id":716,"carID":10,"severity":5,"date":"2020-06-20T00:00:00.000Z"},{"id":717,"carID":1,"severity":2,"date":"2020-06-17T00:00:00.000Z"},{"id":718,"carID":4,"severity":5,"date":"2020-06-04T00:00:00.000Z"},{"id":719,"carID":1,"severity":1,"date":"2020-06-01T00:00:00.000Z"},{"id":720,"carID":8,"severity":2,"date":"2020-06-21T00:00:00.000Z"},{"id":721,"carID":2,"severity":1,"date":"2020-06-03T00:00:00.000Z"},{"id":722,"carID":2,"severity":3,"date":"2020-06-01T00:00:00.000Z"},{"id":723,"carID":12,"severity":1,"date":"2020-06-01T00:00:00.000Z"},{"id":724,"carID":3,"severity":1,"date":"2020-06-04T00:00:00.000Z"},{"id":725,"carID":10,"severity":2,"date":"2020-06-15T00:00:00.000Z"},{"id":726,"carID":5,"severity":5,"date":"2020-06-05T00:00:00.000Z"},{"id":727,"carID":7,"severity":4,"date":"2020-06-18T00:00:00.000Z"},{"id":728,"carID":14,"severity":4,"date":"2020-06-12T00:00:00.000Z"},{"id":729,"carID":7,"severity":2,"date":"2020-06-09T00:00:00.000Z"},{"id":730,"carID":7,"severity":3,"date":"2020-06-08T00:00:00.000Z"},{"id":731,"carID":8,"severity":5,"date":"2020-06-21T00:00:00.000Z"},{"id":732,"carID":11,"severity":3,"date":"2020-06-21T00:00:00.000Z"},{"id":733,"carID":14,"severity":1,"date":"2020-06-01T00:00:00.000Z"},{"id":734,"carID":4,"severity":1,"date":"2020-06-15T00:00:00.000Z"},{"id":735,"carID":8,"severity":2,"date":"2020-06-18T00:00:00.000Z"},{"id":736,"carID":14,"severity":4,"date":"2020-06-21T00:00:00.000Z"},{"id":737,"carID":13,"severity":4,"date":"2020-06-05T00:00:00.000Z"},{"id":738,"carID":9,"severity":4,"date":"2020-06-14T00:00:00.000Z"},{"id":739,"carID":13,"severity":2,"date":"2020-06-01T00:00:00.000Z"},{"id":740,"carID":13,"severity":3,"date":"2020-06-19T00:00:00.000Z"},{"id":741,"carID":10,"severity":4,"date":"2020-06-09T00:00:00.000Z"},{"id":742,"carID":14,"severity":2,"date":"2020-06-12T00:00:00.000Z"},{"id":743,"carID":5,"severity":3,"date":"2020-06-20T00:00:00.000Z"},{"id":744,"carID":2,"severity":3,"date":"2020-06-21T00:00:00.000Z"},{"id":745,"carID":13,"severity":2,"date":"2020-06-16T00:00:00.000Z"},{"id":746,"carID":13,"severity":3,"date":"2020-06-11T00:00:00.000Z"},{"id":747,"carID":14,"severity":3,"date":"2020-06-01T00:00:00.000Z"},{"id":748,"carID":7,"severity":1,"date":"2020-06-06T00:00:00.000Z"},{"id":749,"carID":10,"severity":1,"date":"2020-06-13T00:00:00.000Z"},{"id":750,"carID":3,"severity":1,"date":"2020-06-17T00:00:00.000Z"},{"id":751,"carID":5,"severity":1,"date":"2020-06-10T00:00:00.000Z"},{"id":752,"carID":10,"severity":2,"date":"2020-06-18T00:00:00.000Z"},{"id":753,"carID":13,"severity":5,"date":"2020-06-06T00:00:00.000Z"},{"id":754,"carID":12,"severity":1,"date":"2020-06-16T00:00:00.000Z"},{"id":755,"carID":6,"severity":2,"date":"2020-06-18T00:00:00.000Z"},{"id":756,"carID":9,"severity":3,"date":"2020-06-11T00:00:00.000Z"},{"id":757,"carID":14,"severity":2,"date":"2020-06-04T00:00:00.000Z"},{"id":758,"carID":11,"severity":4,"date":"2020-06-14T00:00:00.000Z"},{"id":759,"carID":14,"severity":1,"date":"2020-06-02T00:00:00.000Z"},{"id":760,"carID":2,"severity":3,"date":"2020-06-13T00:00:00.000Z"},{"id":761,"carID":2,"severity":1,"date":"2020-06-09T00:00:00.000Z"},{"id":762,"carID":9,"severity":3,"date":"2020-06-09T00:00:00.000Z"},{"id":763,"carID":5,"severity":4,"date":"2020-06-07T00:00:00.000Z"},{"id":764,"carID":6,"severity":3,"date":"2020-06-13T00:00:00.000Z"},{"id":765,"carID":9,"severity":4,"date":"2020-06-01T00:00:00.000Z"},{"id":766,"carID":5,"severity":5,"date":"2020-06-17T00:00:00.000Z"},{"id":767,"carID":8,"severity":5,"date":"2020-06-10T00:00:00.000Z"},{"id":768,"carID":7,"severity":1,"date":"2020-06-06T00:00:00.000Z"},{"id":769,"carID":1,"severity":2,"date":"2020-06-11T00:00:00.000Z"},{"id":770,"carID":13,"severity":5,"date":"2020-06-21T00:00:00.000Z"},{"id":771,"carID":12,"severity":3,"date":"2020-06-06T00:00:00.000Z"},{"id":772,"carID":7,"severity":5,"date":"2020-06-03T00:00:00.000Z"},{"id":773,"carID":6,"severity":2,"date":"2020-06-06T00:00:00.000Z"},{"id":774,"carID":8,"severity":3,"date":"2020-06-02T00:00:00.000Z"},{"id":775,"carID":14,"severity":4,"date":"2020-06-12T00:00:00.000Z"},{"id":776,"carID":8,"severity":4,"date":"2020-06-04T00:00:00.000Z"},{"id":777,"carID":13,"severity":2,"date":"2020-06-09T00:00:00.000Z"},{"id":778,"carID":3,"severity":5,"date":"2020-06-11T00:00:00.000Z"},{"id":779,"carID":4,"severity":5,"date":"2020-06-13T00:00:00.000Z"},{"id":780,"carID":3,"severity":3,"date":"2020-06-19T00:00:00.000Z"},{"id":781,"carID":5,"severity":4,"date":"2020-06-21T00:00:00.000Z"},{"id":782,"carID":4,"severity":5,"date":"2020-06-05T00:00:00.000Z"},{"id":783,"carID":6,"severity":5,"date":"2020-06-11T00:00:00.000Z"},{"id":784,"carID":13,"severity":4,"date":"2020-06-13T00:00:00.000Z"},{"id":785,"carID":14,"severity":3,"date":"2020-06-11T00:00:00.000Z"},{"id":786,"carID":8,"severity":4,"date":"2020-06-11T00:00:00.000Z"},{"id":787,"carID":2,"severity":1,"date":"2020-06-08T00:00:00.000Z"},{"id":788,"carID":5,"severity":2,"date":"2020-06-12T00:00:00.000Z"},{"id":789,"carID":8,"severity":5,"date":"2020-06-05T00:00:00.000Z"},{"id":790,"carID":14,"severity":2,"date":"2020-06-11T00:00:00.000Z"},{"id":791,"carID":14,"severity":4,"date":"2020-06-07T00:00:00.000Z"},{"id":792,"carID":8,"severity":2,"date":"2020-06-10T00:00:00.000Z"},{"id":793,"carID":6,"severity":1,"date":"2020-06-14T00:00:00.000Z"},{"id":794,"carID":3,"severity":2,"date":"2020-06-06T00:00:00.000Z"},{"id":795,"carID":8,"severity":1,"date":"2020-06-13T00:00:00.000Z"},{"id":796,"carID":14,"severity":5,"date":"2020-06-05T00:00:00.000Z"},{"id":797,"carID":7,"severity":5,"date":"2020-06-19T00:00:00.000Z"},{"id":798,"carID":9,"severity":5,"date":"2020-06-04T00:00:00.000Z"},{"id":799,"carID":6,"severity":4,"date":"2020-06-15T00:00:00.000Z"},{"id":800,"carID":1,"severity":2,"date":"2020-06-07T00:00:00.000Z"},{"id":801,"carID":5,"severity":3,"date":"2020-06-04T00:00:00.000Z"},{"id":802,"carID":9,"severity":2,"date":"2020-06-14T00:00:00.000Z"},{"id":803,"carID":12,"severity":2,"date":"2020-06-17T00:00:00.000Z"},{"id":804,"carID":3,"severity":2,"date":"2020-06-17T00:00:00.000Z"},{"id":805,"carID":9,"severity":5,"date":"2020-06-21T00:00:00.000Z"},{"id":806,"carID":9,"severity":3,"date":"2020-06-01T00:00:00.000Z"},{"id":807,"carID":12,"severity":2,"date":"2020-06-03T00:00:00.000Z"},{"id":808,"carID":8,"severity":4,"date":"2020-06-13T00:00:00.000Z"},{"id":809,"carID":14,"severity":2,"date":"2020-06-12T00:00:00.000Z"},{"id":810,"carID":8,"severity":1,"date":"2020-06-08T00:00:00.000Z"},{"id":811,"carID":11,"severity":4,"date":"2020-06-09T00:00:00.000Z"},{"id":812,"carID":14,"severity":2,"date":"2020-06-20T00:00:00.000Z"},{"id":813,"carID":5,"severity":1,"date":"2020-06-10T00:00:00.000Z"},{"id":814,"carID":14,"severity":4,"date":"2020-06-19T00:00:00.000Z"},{"id":815,"carID":11,"severity":1,"date":"2020-06-15T00:00:00.000Z"},{"id":816,"carID":6,"severity":1,"date":"2020-06-09T00:00:00.000Z"},{"id":817,"carID":7,"severity":5,"date":"2020-06-07T00:00:00.000Z"},{"id":818,"carID":10,"severity":4,"date":"2020-06-11T00:00:00.000Z"},{"id":819,"carID":3,"severity":2,"date":"2020-06-11T00:00:00.000Z"},{"id":820,"carID":11,"severity":4,"date":"2020-06-20T00:00:00.000Z"},{"id":821,"carID":10,"severity":5,"date":"2020-06-01T00:00:00.000Z"},{"id":822,"carID":10,"severity":1,"date":"2020-06-21T00:00:00.000Z"},{"id":823,"carID":14,"severity":3,"date":"2020-06-20T00:00:00.000Z"},{"id":824,"carID":7,"severity":1,"date":"2020-06-02T00:00:00.000Z"},{"id":825,"carID":8,"severity":3,"date":"2020-06-01T00:00:00.000Z"},{"id":826,"carID":7,"severity":4,"date":"2020-06-11T00:00:00.000Z"},{"id":827,"carID":1,"severity":2,"date":"2020-06-05T00:00:00.000Z"},{"id":828,"carID":1,"severity":3,"date":"2020-06-12T00:00:00.000Z"},{"id":829,"carID":2,"severity":3,"date":"2020-06-18T00:00:00.000Z"},{"id":830,"carID":1,"severity":4,"date":"2020-06-11T00:00:00.000Z"},{"id":831,"carID":8,"severity":1,"date":"2020-06-20T00:00:00.000Z"},{"id":832,"carID":14,"severity":4,"date":"2020-06-04T00:00:00.000Z"},{"id":833,"carID":14,"severity":4,"date":"2020-06-08T00:00:00.000Z"},{"id":834,"carID":12,"severity":5,"date":"2020-06-20T00:00:00.000Z"},{"id":835,"carID":6,"severity":3,"date":"2020-06-02T00:00:00.000Z"},{"id":836,"carID":9,"severity":1,"date":"2020-06-07T00:00:00.000Z"},{"id":837,"carID":2,"severity":2,"date":"2020-06-19T00:00:00.000Z"},{"id":838,"carID":12,"severity":4,"date":"2020-06-16T00:00:00.000Z"},{"id":839,"carID":14,"severity":4,"date":"2020-06-20T00:00:00.000Z"},{"id":840,"carID":2,"severity":2,"date":"2020-06-17T00:00:00.000Z"},{"id":841,"carID":14,"severity":2,"date":"2020-06-12T00:00:00.000Z"},{"id":842,"carID":8,"severity":1,"date":"2020-06-06T00:00:00.000Z"},{"id":843,"carID":14,"severity":2,"date":"2020-06-20T00:00:00.000Z"},{"id":844,"carID":5,"severity":3,"date":"2020-06-16T00:00:00.000Z"},{"id":845,"carID":14,"severity":2,"date":"2020-06-15T00:00:00.000Z"},{"id":846,"carID":3,"severity":4,"date":"2020-06-05T00:00:00.000Z"},{"id":847,"carID":14,"severity":3,"date":"2020-06-11T00:00:00.000Z"},{"id":848,"carID":4,"severity":2,"date":"2020-06-09T00:00:00.000Z"},{"id":849,"carID":10,"severity":1,"date":"2020-06-11T00:00:00.000Z"},{"id":850,"carID":13,"severity":4,"date":"2020-06-09T00:00:00.000Z"},{"id":851,"carID":1,"severity":2,"date":"2020-06-20T00:00:00.000Z"},{"id":852,"carID":10,"severity":5,"date":"2020-06-07T00:00:00.000Z"},{"id":853,"carID":8,"severity":2,"date":"2020-06-18T00:00:00.000Z"},{"id":854,"carID":5,"severity":3,"date":"2020-06-06T00:00:00.000Z"},{"id":855,"carID":2,"severity":2,"date":"2020-06-17T00:00:00.000Z"},{"id":856,"carID":5,"severity":2,"date":"2020-06-04T00:00:00.000Z"},{"id":857,"carID":2,"severity":3,"date":"2020-06-17T00:00:00.000Z"},{"id":858,"carID":7,"severity":2,"date":"2020-06-14T00:00:00.000Z"},{"id":859,"carID":3,"severity":1,"date":"2020-06-13T00:00:00.000Z"},{"id":860,"carID":7,"severity":5,"date":"2020-06-01T00:00:00.000Z"},{"id":861,"carID":2,"severity":2,"date":"2020-06-21T00:00:00.000Z"},{"id":862,"carID":2,"severity":2,"date":"2020-06-21T00:00:00.000Z"},{"id":863,"carID":8,"severity":1,"date":"2020-06-15T00:00:00.000Z"},{"id":864,"carID":5,"severity":5,"date":"2020-06-12T00:00:00.000Z"},{"id":865,"carID":10,"severity":4,"date":"2020-06-06T00:00:00.000Z"},{"id":866,"carID":2,"severity":1,"date":"2020-06-01T00:00:00.000Z"},{"id":867,"carID":12,"severity":3,"date":"2020-06-20T00:00:00.000Z"},{"id":868,"carID":6,"severity":5,"date":"2020-06-03T00:00:00.000Z"},{"id":869,"carID":7,"severity":5,"date":"2020-06-01T00:00:00.000Z"},{"id":870,"carID":8,"severity":2,"date":"2020-06-06T00:00:00.000Z"},{"id":871,"carID":2,"severity":4,"date":"2020-06-18T00:00:00.000Z"},{"id":872,"carID":1,"severity":1,"date":"2020-06-18T00:00:00.000Z"},{"id":873,"carID":7,"severity":3,"date":"2020-06-19T00:00:00.000Z"},{"id":874,"carID":4,"severity":4,"date":"2020-06-19T00:00:00.000Z"},{"id":875,"carID":14,"severity":2,"date":"2020-06-12T00:00:00.000Z"},{"id":876,"carID":1,"severity":2,"date":"2020-06-05T00:00:00.000Z"},{"id":877,"carID":10,"severity":2,"date":"2020-06-13T00:00:00.000Z"},{"id":878,"carID":13,"severity":4,"date":"2020-06-02T00:00:00.000Z"},{"id":879,"carID":13,"severity":5,"date":"2020-06-11T00:00:00.000Z"},{"id":880,"carID":4,"severity":1,"date":"2020-06-13T00:00:00.000Z"},{"id":881,"carID":13,"severity":5,"date":"2020-06-04T00:00:00.000Z"},{"id":882,"carID":10,"severity":5,"date":"2020-06-12T00:00:00.000Z"},{"id":883,"carID":1,"severity":1,"date":"2020-06-20T00:00:00.000Z"},{"id":884,"carID":8,"severity":3,"date":"2020-06-03T00:00:00.000Z"},{"id":885,"carID":12,"severity":5,"date":"2020-06-03T00:00:00.000Z"},{"id":886,"carID":11,"severity":5,"date":"2020-06-10T00:00:00.000Z"},{"id":887,"carID":5,"severity":5,"date":"2020-06-11T00:00:00.000Z"},{"id":888,"carID":10,"severity":4,"date":"2020-06-07T00:00:00.000Z"},{"id":889,"carID":4,"severity":4,"date":"2020-06-09T00:00:00.000Z"},{"id":890,"carID":14,"severity":3,"date":"2020-06-06T00:00:00.000Z"},{"id":891,"carID":8,"severity":3,"date":"2020-06-04T00:00:00.000Z"},{"id":892,"carID":8,"severity":4,"date":"2020-06-19T00:00:00.000Z"},{"id":893,"carID":12,"severity":3,"date":"2020-06-06T00:00:00.000Z"},{"id":894,"carID":12,"severity":2,"date":"2020-06-19T00:00:00.000Z"},{"id":895,"carID":4,"severity":3,"date":"2020-06-19T00:00:00.000Z"},{"id":896,"carID":6,"severity":4,"date":"2020-06-21T00:00:00.000Z"},{"id":897,"carID":8,"severity":2,"date":"2020-06-20T00:00:00.000Z"},{"id":898,"carID":9,"severity":5,"date":"2020-06-13T00:00:00.000Z"},{"id":899,"carID":9,"severity":2,"date":"2020-06-06T00:00:00.000Z"},{"id":900,"carID":14,"severity":1,"date":"2020-06-07T00:00:00.000Z"},{"id":901,"carID":6,"severity":1,"date":"2020-06-18T00:00:00.000Z"},{"id":902,"carID":5,"severity":5,"date":"2020-06-04T00:00:00.000Z"},{"id":903,"carID":6,"severity":4,"date":"2020-06-07T00:00:00.000Z"},{"id":904,"carID":2,"severity":2,"date":"2020-06-06T00:00:00.000Z"},{"id":905,"carID":5,"severity":1,"date":"2020-06-13T00:00:00.000Z"},{"id":906,"carID":12,"severity":3,"date":"2020-06-14T00:00:00.000Z"},{"id":907,"carID":10,"severity":2,"date":"2020-06-20T00:00:00.000Z"},{"id":908,"carID":12,"severity":5,"date":"2020-06-03T00:00:00.000Z"},{"id":909,"carID":3,"severity":2,"date":"2020-06-03T00:00:00.000Z"},{"id":910,"carID":3,"severity":2,"date":"2020-06-11T00:00:00.000Z"},{"id":911,"carID":9,"severity":4,"date":"2020-06-21T00:00:00.000Z"},{"id":912,"carID":5,"severity":5,"date":"2020-06-11T00:00:00.000Z"},{"id":913,"carID":14,"severity":4,"date":"2020-06-12T00:00:00.000Z"},{"id":914,"carID":2,"severity":1,"date":"2020-06-18T00:00:00.000Z"},{"id":915,"carID":2,"severity":5,"date":"2020-06-08T00:00:00.000Z"},{"id":916,"carID":8,"severity":4,"date":"2020-06-01T00:00:00.000Z"},{"id":917,"carID":6,"severity":5,"date":"2020-06-21T00:00:00.000Z"},{"id":918,"carID":14,"severity":5,"date":"2020-06-18T00:00:00.000Z"},{"id":919,"carID":9,"severity":2,"date":"2020-06-01T00:00:00.000Z"},{"id":920,"carID":12,"severity":3,"date":"2020-06-18T00:00:00.000Z"},{"id":921,"carID":13,"severity":5,"date":"2020-06-09T00:00:00.000Z"},{"id":922,"carID":14,"severity":3,"date":"2020-06-16T00:00:00.000Z"},{"id":923,"carID":13,"severity":4,"date":"2020-06-20T00:00:00.000Z"},{"id":924,"carID":10,"severity":5,"date":"2020-06-08T00:00:00.000Z"},{"id":925,"carID":4,"severity":5,"date":"2020-06-05T00:00:00.000Z"},{"id":926,"carID":14,"severity":3,"date":"2020-06-14T00:00:00.000Z"},{"id":927,"carID":2,"severity":2,"date":"2020-06-17T00:00:00.000Z"},{"id":928,"carID":14,"severity":2,"date":"2020-06-11T00:00:00.000Z"},{"id":929,"carID":1,"severity":3,"date":"2020-06-20T00:00:00.000Z"},{"id":930,"carID":14,"severity":4,"date":"2020-06-12T00:00:00.000Z"},{"id":931,"carID":11,"severity":3,"date":"2020-06-13T00:00:00.000Z"},{"id":932,"carID":5,"severity":3,"date":"2020-06-08T00:00:00.000Z"},{"id":933,"carID":14,"severity":4,"date":"2020-06-14T00:00:00.000Z"},{"id":934,"carID":13,"severity":5,"date":"2020-06-20T00:00:00.000Z"},{"id":935,"carID":11,"severity":4,"date":"2020-06-13T00:00:00.000Z"},{"id":936,"carID":9,"severity":5,"date":"2020-06-12T00:00:00.000Z"},{"id":937,"carID":1,"severity":2,"date":"2020-06-10T00:00:00.000Z"},{"id":938,"carID":7,"severity":5,"date":"2020-06-18T00:00:00.000Z"},{"id":939,"carID":14,"severity":3,"date":"2020-06-02T00:00:00.000Z"},{"id":940,"carID":3,"severity":5,"date":"2020-06-14T00:00:00.000Z"},{"id":941,"carID":1,"severity":2,"date":"2020-06-04T00:00:00.000Z"},{"id":942,"carID":1,"severity":3,"date":"2020-06-16T00:00:00.000Z"},{"id":943,"carID":7,"severity":1,"date":"2020-06-17T00:00:00.000Z"},{"id":944,"carID":13,"severity":2,"date":"2020-06-08T00:00:00.000Z"},{"id":945,"carID":2,"severity":4,"date":"2020-06-10T00:00:00.000Z"},{"id":946,"carID":9,"severity":5,"date":"2020-06-07T00:00:00.000Z"},{"id":947,"carID":1,"severity":5,"date":"2020-06-13T00:00:00.000Z"},{"id":948,"carID":4,"severity":1,"date":"2020-06-03T00:00:00.000Z"},{"id":949,"carID":10,"severity":3,"date":"2020-06-20T00:00:00.000Z"},{"id":950,"carID":14,"severity":4,"date":"2020-06-08T00:00:00.000Z"},{"id":951,"carID":7,"severity":3,"date":"2020-06-06T00:00:00.000Z"},{"id":952,"carID":13,"severity":2,"date":"2020-06-03T00:00:00.000Z"},{"id":953,"carID":6,"severity":3,"date":"2020-06-06T00:00:00.000Z"},{"id":954,"carID":14,"severity":3,"date":"2020-06-17T00:00:00.000Z"},{"id":955,"carID":12,"severity":5,"date":"2020-06-17T00:00:00.000Z"},{"id":956,"carID":2,"severity":1,"date":"2020-06-06T00:00:00.000Z"},{"id":957,"carID":4,"severity":5,"date":"2020-06-18T00:00:00.000Z"},{"id":958,"carID":13,"severity":3,"date":"2020-06-20T00:00:00.000Z"},{"id":959,"carID":14,"severity":1,"date":"2020-06-05T00:00:00.000Z"},{"id":960,"carID":11,"severity":3,"date":"2020-06-06T00:00:00.000Z"},{"id":961,"carID":9,"severity":5,"date":"2020-06-15T00:00:00.000Z"},{"id":962,"carID":11,"severity":1,"date":"2020-06-19T00:00:00.000Z"},{"id":963,"carID":8,"severity":2,"date":"2020-06-06T00:00:00.000Z"},{"id":964,"carID":10,"severity":3,"date":"2020-06-14T00:00:00.000Z"},{"id":965,"carID":14,"severity":1,"date":"2020-06-02T00:00:00.000Z"},{"id":966,"carID":14,"severity":2,"date":"2020-06-01T00:00:00.000Z"},{"id":967,"carID":11,"severity":4,"date":"2020-06-01T00:00:00.000Z"},{"id":968,"carID":12,"severity":3,"date":"2020-06-14T00:00:00.000Z"},{"id":969,"carID":10,"severity":1,"date":"2020-06-05T00:00:00.000Z"},{"id":970,"carID":2,"severity":3,"date":"2020-06-11T00:00:00.000Z"},{"id":971,"carID":11,"severity":2,"date":"2020-06-13T00:00:00.000Z"},{"id":972,"carID":9,"severity":1,"date":"2020-06-02T00:00:00.000Z"},{"id":973,"carID":7,"severity":4,"date":"2020-06-03T00:00:00.000Z"},{"id":974,"carID":1,"severity":4,"date":"2020-06-21T00:00:00.000Z"},{"id":975,"carID":9,"severity":5,"date":"2020-06-20T00:00:00.000Z"},{"id":976,"carID":2,"severity":5,"date":"2020-06-04T00:00:00.000Z"},{"id":977,"carID":5,"severity":4,"date":"2020-06-14T00:00:00.000Z"},{"id":978,"carID":14,"severity":5,"date":"2020-06-03T00:00:00.000Z"},{"id":979,"carID":7,"severity":1,"date":"2020-06-09T00:00:00.000Z"},{"id":980,"carID":7,"severity":1,"date":"2020-06-19T00:00:00.000Z"},{"id":981,"carID":3,"severity":5,"date":"2020-06-11T00:00:00.000Z"},{"id":982,"carID":7,"severity":2,"date":"2020-06-06T00:00:00.000Z"},{"id":983,"carID":13,"severity":3,"date":"2020-06-19T00:00:00.000Z"},{"id":984,"carID":3,"severity":5,"date":"2020-06-20T00:00:00.000Z"},{"id":985,"carID":7,"severity":4,"date":"2020-06-13T00:00:00.000Z"},{"id":986,"carID":7,"severity":3,"date":"2020-06-12T00:00:00.000Z"},{"id":987,"carID":4,"severity":1,"date":"2020-06-14T00:00:00.000Z"},{"id":988,"carID":10,"severity":3,"date":"2020-06-14T00:00:00.000Z"},{"id":989,"carID":9,"severity":5,"date":"2020-06-15T00:00:00.000Z"},{"id":990,"carID":5,"severity":3,"date":"2020-06-20T00:00:00.000Z"},{"id":991,"carID":14,"severity":3,"date":"2020-06-21T00:00:00.000Z"},{"id":992,"carID":10,"severity":1,"date":"2020-06-08T00:00:00.000Z"},{"id":993,"carID":10,"severity":5,"date":"2020-06-12T00:00:00.000Z"},{"id":994,"carID":4,"severity":1,"date":"2020-06-17T00:00:00.000Z"},{"id":995,"carID":9,"severity":2,"date":"2020-06-09T00:00:00.000Z"},{"id":996,"carID":14,"severity":4,"date":"2020-06-21T00:00:00.000Z"},{"id":997,"carID":14,"severity":3,"date":"2020-06-09T00:00:00.000Z"},{"id":998,"carID":6,"severity":5,"date":"2020-06-14T00:00:00.000Z"},{"id":999,"carID":2,"severity":1,"date":"2020-06-06T00:00:00.000Z"},{"id":1000,"carID":11,"severity":3,"date":"2020-06-21T00:00:00.000Z"}]